uy/__init__.py
uy-0.0.5.dist-info/licenses/LICENSE
uy-0.0.5.dist-info/METADATA
uy-0.0.5.dist-info/WHEEL
uy-0.0.5.dist-info/top_level.txt
uy-0.0.5.dist-info/RECORD
