Metadata-Version: 2.4
Name: uy
Version: 0.0.5
Summary: Based on https://github.com/pbharrin/machinelearninginaction/blob/master/Ch12/fpGrowth.py
Home-page: https://github.com/t-c-w/uy
Author: Thor Whalen
License: apache-2.0
Platform: any
License-File: LICENSE
Dynamic: license-file
